hcorex/__init__.py
hcorex/hcorex.cpython-36m-x86_64-linux-gnu.so
hcorex/init.cpython-36m-x86_64-linux-gnu.so
hcorex-0.0.0.5.dist-info/METADATA
hcorex-0.0.0.5.dist-info/WHEEL
hcorex-0.0.0.5.dist-info/top_level.txt
hcorex-0.0.0.5.dist-info/RECORD
