Metadata-Version: 2.1
Name: hcorex
Version: 0.0.0.5
Summary: hcore
Home-page: https://pypi.org/user/gsmomo/
Author: zgs
Author-email: UNKNOWN
License: BSD License
Platform: all
Classifier: Operating System :: OS Independent
Classifier: Intended Audience :: Developers
Classifier: License :: OSI Approved :: BSD License
Classifier: Programming Language :: Python :: 3.6
